toonapi/__init__.py
toonapi/__version__.py
toonapi/const.py
toonapi/exceptions.py
toonapi/models.py
toonapi/toon.py
toonapi/util.py
toonapi-0.3.0.dist-info/LICENSE.md
toonapi-0.3.0.dist-info/METADATA
toonapi-0.3.0.dist-info/WHEEL
toonapi-0.3.0.dist-info/top_level.txt
toonapi-0.3.0.dist-info/RECORD
