Metadata-Version: 2.1
Name: toonapi
Version: 0.3.0
Summary: Asynchronous Python client for the Quby ToonAPI.
Home-page: https://github.com/frenck/python-toonapi
Author: Franck Nijhof
Author-email: opensource@frenck.dev
License: MIT license
Keywords: toon,quby,eneco,boxx,engie,electrabel,viesgo,toonapi,api,async,client
Platform: UNKNOWN
Classifier: Development Status :: 4 - Beta
Classifier: Framework :: AsyncIO
Classifier: Intended Audience :: Developers
Classifier: License :: OSI Approved :: MIT License
Classifier: Natural Language :: English
Classifier: Programming Language :: Python :: 3.8
Classifier: Programming Language :: Python :: 3.9
Classifier: Programming Language :: Python :: 3.10
Classifier: Programming Language :: Python :: 3.11
Classifier: Programming Language :: Python :: 3.12
Classifier: Programming Language :: Python :: 3
Classifier: Topic :: Software Development :: Libraries :: Python Modules
